yesdomainfinder/__init__.py
yesdomainfinder/cli.py
yesdomaininfo-2.0.0.dist-info/licenses/LICENSE
yesdomaininfo-2.0.0.dist-info/METADATA
yesdomaininfo-2.0.0.dist-info/WHEEL
yesdomaininfo-2.0.0.dist-info/entry_points.txt
yesdomaininfo-2.0.0.dist-info/top_level.txt
yesdomaininfo-2.0.0.dist-info/RECORD
