Metadata-Version: 2.4
Name: yesdomaininfo
Version: 2.0.0
Summary: Professional Domain Investigation Tool
Home-page: https://github.com/yesvanshzoffical/yesdomainfinder
Author: YesVanshz
Requires-Python: >=3.6
License-File: LICENSE
Requires-Dist: requests
Requires-Dist: dnspython
Requires-Dist: python-whois
Requires-Dist: rich
Dynamic: author
Dynamic: description
Dynamic: description-content-type
Dynamic: home-page
Dynamic: license-file
Dynamic: requires-dist
Dynamic: requires-python
Dynamic: summary
